[
    {
        "jobId": 12345,
        "status": "approved",
        "datePosted": "September 12th 2023, 10:22:36 am",
        "title": "Software Engineer",
        "companyDetails": "A leading tech company",
        "companyName": "TechCo Inc.",
        "jobLocation": "Remote",
        "employmentType": "full-time",
        "applicationDeadline": "October 1st 2023, 11:59:59 pm",
        "category": "Technology",
        "experience": "3+ years",
        "vacancies": 3,
        "requiredSkills": [
            "Java",
            "Python",
            "Web Development"
        ],
        "salary": "$80,000 - $100,000",
        "authorEmail": "hr@techco.com",
        "instructions": "Please send your resume and cover letter to hr@techco.com.",
        "jobsDescription": "TechCo Inc. is looking for experienced software engineers to join our remote team."
    },
    {
        "jobId": 23456,
        "status": "approved",
        "datePosted": "September 11th 2023, 3:45:20 pm",
        "title": "Graphic Designer",
        "companyDetails": "A creative design agency",
        "companyName": "DesignHub",
        "jobLocation": "On-site",
        "employmentType": "full-time",
        "applicationDeadline": "September 30th 2023, 5:00:00 pm",
        "category": "Design",
        "experience": "2+ years",
        "vacancies": 2,
        "requiredSkills": [
            "Adobe Photoshop",
            "Illustrator",
            "UI/UX Design"
        ],
        "salary": "$50,000 - $65,000",
        "authorEmail": "hr@designhub.com",
        "instructions": "Submit your portfolio and resume to hr@designhub.com.",
        "jobsDescription": "DesignHub is seeking talented graphic designers for on-site positions."
    },
    {
        "jobId": 34567,
        "status": "pending",
        "datePosted": "September 10th 2023, 1:30:15 pm",
        "title": "Data Analyst",
        "companyDetails": "A data-driven startup",
        "companyName": "DataTech",
        "jobLocation": "Remote",
        "employmentType": "part-time",
        "applicationDeadline": "September 25th 2023, 6:00:00 pm",
        "category": "Data Science",
        "experience": "1+ year",
        "vacancies": 1,
        "requiredSkills": [
            "SQL",
            "Data Visualization",
            "Statistics"
        ],
        "salary": "$40,000 - $50,000",
        "authorEmail": "hr@datatech.com",
        "instructions": "Send your resume and a sample analysis report to hr@datatech.com.",
        "jobsDescription": "DataTech is in search of a remote part-time data analyst to join our team."
    },
    {
        "jobId": 45678,
        "status": "approved",
        "datePosted": "September 9th 2023, 11:15:42 am",
        "title": "Marketing Manager",
        "companyDetails": "A growing marketing agency",
        "companyName": "MarketingPro",
        "jobLocation": "On-site",
        "employmentType": "full-time",
        "applicationDeadline": "September 28th 2023, 4:30:00 pm",
        "category": "Marketing",
        "experience": "5+ years",
        "vacancies": 1,
        "requiredSkills": [
            "Digital Marketing",
            "SEO",
            "Content Strategy"
        ],
        "salary": "$70,000 - $90,000",
        "authorEmail": "hr@marketingpro.com",
        "instructions": "Submit your resume and a marketing campaign portfolio to hr@marketingpro.com.",
        "jobsDescription": "MarketingPro is hiring a full-time marketing manager for on-site work."
    },
    {
        "jobId": 56789,
        "status": "approved",
        "datePosted": "September 8th 2023, 2:55:10 pm",
        "title": "Customer Support Representative",
        "companyDetails": "A leading e-commerce company",
        "companyName": "ShopZone",
        "jobLocation": "Remote",
        "employmentType": "part-time",
        "applicationDeadline": "September 27th 2023, 7:00:00 pm",
        "category": "Customer Service",
        "experience": "1+ year",
        "vacancies": 5,
        "requiredSkills": [
            "Customer Service",
            "Communication",
            "Problem Solving"
        ],
        "salary": "$30,000 - $35,000",
        "authorEmail": "hr@shopzone.com",
        "instructions": "Send your resume and a brief cover letter to hr@shopzone.com.",
        "jobsDescription": "ShopZone is seeking remote part-time customer support representatives to assist our customers."
    },
    {
        "jobId": 67890,
        "status": "pending",
        "datePosted": "September 7th 2023, 9:10:55 am",
        "title": "Accountant",
        "companyDetails": "A reputable accounting firm",
        "companyName": "AccountWise",
        "jobLocation": "On-site",
        "employmentType": "full-time",
        "applicationDeadline": "September 26th 2023, 3:45:00 pm",
        "category": "Finance",
        "experience": "3+ years",
        "vacancies": 1,
        "requiredSkills": [
            "Accounting",
            "Financial Analysis",
            "Taxation"
        ],
        "salary": "$60,000 - $75,000",
        "authorEmail": "hr@accountwise.com",
        "instructions": "Submit your resume and references to hr@accountwise.com.",
        "jobsDescription": "AccountWise is looking for an experienced accountant for on-site work."
    },
    {
        "jobId": 78901,
        "status": "approved",
        "datePosted": "September 6th 2023, 4:20:30 pm",
        "title": "Software Quality Assurance Tester",
        "companyDetails": "A software development company",
        "companyName": "DevSoft",
        "jobLocation": "Remote",
        "employmentType": "full-time",
        "applicationDeadline": "September 24th 2023, 6:30:00 pm",
        "category": "Technology",
        "experience": "2+ years",
        "vacancies": 2,
        "requiredSkills": [
            "QA Testing",
            "Test Automation",
            "Bug Tracking"
        ],
        "salary": "$45,000 - $60,000",
        "authorEmail": "hr@devsoft.com",
        "instructions": "Send your resume and a sample test plan to hr@devsoft.com.",
        "jobsDescription": "DevSoft is hiring remote software quality assurance testers for full-time positions."
    },
    {
        "jobId": 89012,
        "status": "approved",
        "datePosted": "September 5th 2023, 8:05:50 am",
        "title": "HR Specialist",
        "companyDetails": "A multinational corporation",
        "companyName": "GlobalCorp",
        "jobLocation": "On-site",
        "employmentType": "full-time",
        "applicationDeadline": "September 23rd 2023, 5:15:00 pm",
        "category": "Human Resources",
        "experience": "3+ years",
        "vacancies": 1,
        "requiredSkills": [
            "HR Policies",
            "Recruitment",
            "Employee Relations"
        ],
        "salary": "$55,000 - $70,000",
        "authorEmail": "hr@globalcorp.com",
        "instructions": "Submit your resume and a cover letter detailing your HR experience to hr@globalcorp.com.",
        "jobsDescription": "GlobalCorp is looking for an HR specialist to join our on-site team."
    },
    {
        "jobId": 90123,
        "status": "pending",
        "datePosted": "September 4th 2023, 12:00:05 pm",
        "title": "Content Writer",
        "companyDetails": "A content marketing agency",
        "companyName": "ContentWave",
        "jobLocation": "Remote",
        "employmentType": "part-time",
        "applicationDeadline": "September 22nd 2023, 4:00:00 pm",
        "category": "Writing",
        "experience": "2+ years",
        "vacancies": 3,
        "requiredSkills": [
            "Content Creation",
            "SEO Writing",
            "Editing"
        ],
        "salary": "$35,000 - $45,000",
        "authorEmail": "hr@contentwave.com",
        "instructions": "Send your resume and writing portfolio to hr@contentwave.com.",
        "jobsDescription": "ContentWave is seeking remote part-time content writers with experience in SEO writing."
    },
    {
        "jobId": 31234,
        "status": "approved",
        "datePosted": "September 3rd 2023, 3:15:25 pm",
        "title": "Sales Representative",
        "companyDetails": "A growing sales team",
        "companyName": "SalesPro",
        "jobLocation": "On-site",
        "employmentType": "full-time",
        "applicationDeadline": "September 21st 2023, 3:30:00 pm",
        "category": "Sales",
        "experience": "1+ year",
        "vacancies": 4,
        "requiredSkills": [
            "Sales",
            "Customer Relations",
            "Negotiation"
        ],
        "salary": "$40,000 - $55,000",
        "authorEmail": "hr@salespro.com",
        "instructions": "Submit your resume and a sales pitch example to hr@salespro.com.",
        "jobsDescription": "SalesPro is hiring on-site full-time sales representatives to join our team."
    },
    {
        "jobId": 34567,
        "status": "approved",
        "datePosted": "September 2nd 2023, 10:50:15 am",
        "title": "Frontend Developer",
        "companyDetails": "A web development agency",
        "companyName": "WebWizards",
        "jobLocation": "Remote",
        "employmentType": "full-time",
        "applicationDeadline": "September 20th 2023, 6:00:00 pm",
        "category": "Technology",
        "experience": "3+ years",
        "vacancies": 2,
        "requiredSkills": [
            "HTML",
            "CSS",
            "JavaScript"
        ],
        "salary": "$60,000 - $75,000",
        "authorEmail": "hr@webwizards.com",
        "instructions": "Send your resume and a link to your portfolio to hr@webwizards.com.",
        "jobsDescription": "WebWizards is looking for experienced frontend developers for remote full-time positions."
    },
    {
        "jobId": 45678,
        "status": "pending",
        "datePosted": "September 1st 2023, 1:00:55 pm",
        "title": "Product Manager",
        "companyDetails": "A technology startup",
        "companyName": "TechStart",
        "jobLocation": "On-site",
        "employmentType": "full-time",
        "applicationDeadline": "September 19th 2023, 5:30:00 pm",
        "category": "Product Management",
        "experience": "5+ years",
        "vacancies": 1,
        "requiredSkills": [
            "Product Development",
            "Team Leadership",
            "Market Research"
        ],
        "salary": "$80,000 - $100,000",
        "authorEmail": "hr@techstart.com",
        "instructions": "Submit your resume and a product strategy document to hr@techstart.com.",
        "jobsDescription": "TechStart is seeking an on-site product manager with extensive experience."
    },
    {
        "jobId": 56789,
        "status": "approved",
        "datePosted": "August 31st 2023, 5:30:40 pm",
        "title": "Data Scientist",
        "companyDetails": "A data analytics company",
        "companyName": "DataInsights",
        "jobLocation": "Remote",
        "employmentType": "full-time",
        "applicationDeadline": "September 18th 2023, 7:45:00 pm",
        "category": "Data Science",
        "experience": "3+ years",
        "vacancies": 2,
        "requiredSkills": [
            "Machine Learning",
            "Data Analysis",
            "Python"
        ],
        "salary": "$70,000 - $90,000",
        "authorEmail": "hr@datainsights.com",
        "instructions": "Send your resume and a data analysis project to hr@datainsights.com.",
        "jobsDescription": "DataInsights is hiring remote data scientists with expertise in machine learning."
    },
    {
        "jobId": 67890,
        "status": "approved",
        "datePosted": "August 30th 2023, 8:40:20 am",
        "title": "Legal Counsel",
        "companyDetails": "A law firm specializing in corporate law",
        "companyName": "LegalSolutions",
        "jobLocation": "On-site",
        "employmentType": "full-time",
        "applicationDeadline": "September 17th 2023, 4:15:00 pm",
        "category": "Legal",
        "experience": "4+ years",
        "vacancies": 1,
        "requiredSkills": [
            "Corporate Law",
            "Legal Research",
            "Contract Drafting"
        ],
        "salary": "$90,000 - $110,000",
        "authorEmail": "hr@legalsolutions.com",
        "instructions": "Submit your resume and a legal case study analysis to hr@legalsolutions.com.",
        "jobsDescription": "LegalSolutions is seeking an on-site legal counsel with corporate law expertise."
    },
    {
        "jobId": 78901,
        "status": "pending",
        "datePosted": "August 29th 2023, 12:15:10 pm",
        "title": "UX/UI Designer",
        "companyDetails": "A UX/UI design agency",
        "companyName": "DesignStudio",
        "jobLocation": "Remote",
        "employmentType": "part-time",
        "applicationDeadline": "September 16th 2023, 6:30:00 pm",
        "category": "Design",
        "experience": "2+ years",
        "vacancies": 2,
        "requiredSkills": [
            "UI/UX Design",
            "Prototyping",
            "User Research"
        ],
        "salary": "$50,000 - $65,000",
        "authorEmail": "hr@designstudio.com",
        "instructions": "Send your resume and a design portfolio to hr@designstudio.com.",
        "jobsDescription": "DesignStudio is seeking remote part-time UX/UI designers with creative flair."
    },
    {
        "jobId": 89012,
        "status": "approved",
        "datePosted": "August 28th 2023, 3:00:35 pm",
        "title": "Customer Success Manager",
        "companyDetails": "A SaaS company",
        "companyName": "SaaSolutions",
        "jobLocation": "On-site",
        "employmentType": "full-time",
        "applicationDeadline": "September 15th 2023, 5:00:00 pm",
        "category": "Customer Success",
        "experience": "3+ years",
        "vacancies": 1,
        "requiredSkills": [
            "Customer Relationship Management",
            "Product Knowledge",
            "Problem Resolution"
        ],
        "salary": "$65,000 - $80,000",
        "authorEmail": "hr@saasolutions.com",
        "instructions": "Submit your resume and a customer success case study to hr@saasolutions.com.",
        "jobsDescription": "SaaSolutions is hiring a full-time customer success manager for on-site work."
    }
]